max_contrast.py
max_contrast-0.0.2.dist-info/LICENSE
max_contrast-0.0.2.dist-info/METADATA
max_contrast-0.0.2.dist-info/WHEEL
max_contrast-0.0.2.dist-info/top_level.txt
max_contrast-0.0.2.dist-info/RECORD
