Metadata-Version: 2.1
Name: max-contrast
Version: 0.0.2
Summary: Library which replicates the Paint.net contrast & brightness functionality in Python, allowing you to increase the contrast of an image until it turns B&W.
Home-page: https://github.com/delivey/max-contrast
Author: delivey
License: MIT
Classifier: Programming Language :: Python :: 3
Classifier: License :: OSI Approved :: MIT License
Classifier: Operating System :: OS Independent
Requires-Python: >=3.6
License-File: LICENSE
Requires-Dist: Pillow
